flask_yamlpage
