Metadata-Version: 1.1
Name: flask-yamlpage
Version: 0.0.3
Summary: Flatpages in yaml syntax
Home-page: https://github.com/imbolc/flask-yamlpage
Author: Imbolc
Author-email: imbolc@imbolc.name
License: MIT
Platform: UNKNOWN
Classifier: Development Status :: 4 - Beta
Classifier: Intended Audience :: Developers
Classifier: License :: OSI Approved :: ISC License (ISCL)
Classifier: Programming Language :: Python
